spado.py
spado-0.1.3.dist-info/LICENSE.md
spado-0.1.3.dist-info/WHEEL
spado-0.1.3.dist-info/METADATA
spado-0.1.3.dist-info/RECORD
