Metadata-Version: 2.1
Name: spado
Version: 0.1.3
Summary: Client simplifying and abstracting common operations for digital ocean spaces.
Home-page: https://github.com/alexpdr/spado
License: GPL-3.0-or-later
Author: Alex Pedersen
Author-email: me@alexpdr.dev
Maintainer: Alex Pedersen
Maintainer-email: me@alexpdr.dev
Requires-Python: >=3.8,<4.0
Classifier: License :: OSI Approved :: GNU General Public License v3 or later (GPLv3+)
Classifier: Programming Language :: Python :: 3
Classifier: Programming Language :: Python :: 3.8
Requires-Dist: boto3 (>=1.13.8,<2.0.0)
Project-URL: Repository, https://github.com/alexpdr/spado
